core_tests/__init__.py
core_tests/py.typed
core_tests/tests/__init__.py
core_tests/tests/base.py
core_tests/tests/runner.py
core_tests-2.0.4.dist-info/licenses/LICENSE
core_tests-2.0.4.dist-info/METADATA
core_tests-2.0.4.dist-info/WHEEL
core_tests-2.0.4.dist-info/top_level.txt
core_tests-2.0.4.dist-info/RECORD
