Metadata-Version: 2.4
Name: core-tests
Version: 2.0.4
Summary: It contains common elements for testing purposes...
Author-email: Alejandro Cora González <alek.cora.glez@gmail.com>
Maintainer: Alejandro Cora González
License-Expression: MIT
Project-URL: Homepage, https://gitlab.com/bytecode-solutions/core/core-tests
Project-URL: Repository, https://gitlab.com/bytecode-solutions/core/core-tests
Project-URL: Documentation, https://core-tests.readthedocs.io/en/latest/
Project-URL: Issues, https://gitlab.com/bytecode-solutions/core/core-tests/-/issues
Project-URL: Changelog, https://gitlab.com/bytecode-solutions/core/core-tests/-/blob/master/CHANGELOG.md
Classifier: Intended Audience :: Developers
Classifier: Development Status :: 5 - Production/Stable
Classifier: Topic :: Software Development :: Libraries :: Python Modules
Classifier: Topic :: Utilities
Classifier: Programming Language :: Python
Classifier: Programming Language :: Python :: 3
Classifier: Programming Language :: Python :: 3 :: Only
Classifier: Programming Language :: Python :: 3.9
Classifier: Programming Language :: Python :: 3.10
Classifier: Programming Language :: Python :: 3.11
Classifier: Programming Language :: Python :: 3.12
Classifier: Programming Language :: Python :: 3.13
Requires-Python: >=3.9
License-File: LICENSE
Requires-Dist: click>=8.1.8
Requires-Dist: coverage>=7.7.1
Requires-Dist: environs>=14.1.1
Requires-Dist: pytest>=7.4.0
Requires-Dist: pytest-xdist>=3.5.0
Provides-Extra: dev
Requires-Dist: core-dev-tools>=1.0.1; extra == "dev"
Dynamic: license-file
